aiohttp_client_rate_limiter/ClientSession.py
aiohttp_client_rate_limiter/__init__.py
aiohttp_client_rate_limiter-1.0.3.dist-info/METADATA
aiohttp_client_rate_limiter-1.0.3.dist-info/WHEEL
aiohttp_client_rate_limiter-1.0.3.dist-info/licenses/LICENSE
aiohttp_client_rate_limiter-1.0.3.dist-info/RECORD
