Metadata-Version: 2.1
Name: aiohttp_client_rate_limiter
Version: 1.0.3
Summary: This is a mini tool that overwrite aiohttp session to provide rate limit function within a same session.
Project-URL: Homepage, https://github.com/peteropensource/aiohttp_rate_limiter
Author-email: Peter Lee <info@peterlee.space>
License-File: LICENSE
Classifier: License :: OSI Approved :: Apache Software License
Classifier: Operating System :: OS Independent
Classifier: Programming Language :: Python :: 3
Requires-Python: >=3.7
